crypto_test/__init__.py
crypto_test-1.0.0.dist-info/DESCRIPTION.rst
crypto_test-1.0.0.dist-info/METADATA
crypto_test-1.0.0.dist-info/RECORD
crypto_test-1.0.0.dist-info/WHEEL
crypto_test-1.0.0.dist-info/metadata.json
crypto_test-1.0.0.dist-info/top_level.txt
