Metadata-Version: 2.0
Name: crypto-test
Version: 1.0.0
Summary: The easiest way to integrate Crypto Wallet Api Functions in your applications. Sign up at Cryptowallet.com for your API key.
Home-page: UNKNOWN
Author: Pravin J
Author-email: pravintest3@gmail.com
License: ISC
Platform: UNKNOWN
Requires-Dist: base58
Requires-Dist: ecdsa
Requires-Dist: pycrypto
Requires-Dist: requests
Requires-Dist: six
